{
  "latest_qr": null,
  "photos": [
    {
      "id": "3f5f05bd-fc5f-439a-82fe-3b10fe316ba9",
      "pickup_code": "AC73A541",
      "filenames": [
        "20260206_054018_AC73A541_1.png"
      ],
      "timestamp": "2026-02-06T05:40:18.361030",
      "time_display": "05:40:18 06/02/2026",
      "qr_url": "http://us1.bot-hosting.net:21555/scan/AC73A541",
      "download_count": 0
    },
    {
      "id": "bd164115-ec29-4468-a187-56679b060357",
      "pickup_code": "E4B75F96",
      "filenames": [
        "20260206_054528_E4B75F96_1.png",
        "20260206_054528_E4B75F96_2.png"
      ],
      "timestamp": "2026-02-06T05:45:28.953742",
      "time_display": "05:45:28 06/02/2026",
      "qr_url": "http://us1.bot-hosting.net:21555/scan/E4B75F96",
      "download_count": 0
    },
    {
      "id": "2aefcc44-35c3-42fa-8be5-e6757758bc3f",
      "pickup_code": "2EE91D00",
      "filenames": [
        "20260206_055204_2EE91D00_1.png",
        "20260206_055204_2EE91D00_2.png"
      ],
      "timestamp": "2026-02-06T05:52:04.454607",
      "time_display": "05:52:04 06/02/2026",
      "qr_url": "http://us1.bot-hosting.net:21555/scan/2EE91D00",
      "download_count": 0
    },
    {
      "id": "c7990183-4eff-466d-bce3-ceb3215ce787",
      "pickup_code": "B1DF6502",
      "filenames": [
        "20260206_055429_B1DF6502_1.png"
      ],
      "timestamp": "2026-02-06T05:54:29.164553",
      "time_display": "05:54:29 06/02/2026",
      "qr_url": "http://us1.bot-hosting.net:21555/scan/B1DF6502",
      "download_count": 0
    },
    {
      "id": "f1647805-5104-431e-bece-2197c88d162c",
      "pickup_code": "F1EDEBC5",
      "filenames": [
        "20260206_064050_F1EDEBC5_retake_1.png"
      ],
      "timestamp": "2026-02-06T06:40:50.194693",
      "time_display": "06:40:50 06/02/2026",
      "qr_url": "http://us1.bot-hosting.net:21555/scan/F1EDEBC5",
      "download_count": 0,
      "retake_used": true
    },
    {
      "id": "e522a0a9-e657-41f6-b27b-257624a94c27",
      "pickup_code": "C25D6B3C",
      "filenames": [
        "20260206_064228_C25D6B3C_1.png"
      ],
      "timestamp": "2026-02-06T06:42:28.542849",
      "time_display": "06:42:28 06/02/2026",
      "qr_url": "http://us1.bot-hosting.net:21555/scan/C25D6B3C",
      "download_count": 0,
      "retake_used": false
    },
    {
      "id": "3dfafb20-8412-40f1-a4ec-9f341ebf8227",
      "pickup_code": "44F6C536",
      "filenames": [
        "20260206_071715_44F6C536_1.png"
      ],
      "timestamp": "2026-02-06T07:17:15.646804",
      "time_display": "07:17:15 06/02/2026",
      "qr_url": "http://us1.bot-hosting.net:21555/scan/44F6C536",
      "download_count": 0,
      "retake_used": false
    },
    {
      "id": "254697ef-5043-45fe-864a-c23a42849e89",
      "pickup_code": "E1F86021",
      "filenames": [
        "20260206_073659_E1F86021_1.png"
      ],
      "timestamp": "2026-02-06T07:36:59.371573",
      "time_display": "07:36:59 06/02/2026",
      "qr_url": "http://us1.bot-hosting.net:21555/scan/E1F86021",
      "download_count": 0,
      "retake_used": false
    },
    {
      "id": "fe73f445-758e-4879-a2a3-479118078e49",
      "pickup_code": "BB567561",
      "filenames": [
        "20260206_073742_BB567561_1.png"
      ],
      "timestamp": "2026-02-06T07:37:42.170919",
      "time_display": "07:37:42 06/02/2026",
      "qr_url": "http://us1.bot-hosting.net:21555/scan/BB567561",
      "download_count": 0,
      "retake_used": false
    },
    {
      "id": "199847b0-9971-4f00-abd0-d5dbaa7adc73",
      "pickup_code": "165AAB25",
      "filenames": [
        "20260206_074045_165AAB25_1.png"
      ],
      "timestamp": "2026-02-06T07:40:45.169677",
      "time_display": "07:40:45 06/02/2026",
      "qr_url": "http://us1.bot-hosting.net:21555/scan/165AAB25",
      "download_count": 0,
      "retake_used": false
    },
    {
      "id": "8e6f3917-25f7-4d87-92ff-a2cba64ff4ed",
      "pickup_code": "28E2F20A",
      "filenames": [
        "20260206_075011_28E2F20A_1.png"
      ],
      "timestamp": "2026-02-06T07:50:11.947755",
      "time_display": "07:50:11 06/02/2026",
      "qr_url": "http://us1.bot-hosting.net:21555/scan/28E2F20A",
      "download_count": 0,
      "retake_used": false
    },
    {
      "id": "a96bd5a0-5130-4cc9-83f8-76a09508622b",
      "pickup_code": "8F03DB42",
      "filenames": [
        "20260206_075808_8F03DB42_1.png"
      ],
      "timestamp": "2026-02-06T07:58:08.554328",
      "time_display": "07:58:08 06/02/2026",
      "qr_url": "http://us1.bot-hosting.net:21555/scan/8F03DB42",
      "download_count": 0,
      "retake_used": false
    },
    {
      "id": "99684fca-3fc4-4624-aa16-d781fac09526",
      "pickup_code": "DE25438F",
      "filenames": [
        "20260207_031706_DE25438F_1.png"
      ],
      "timestamp": "2026-02-07T03:17:06.801850",
      "time_display": "03:17:06 07/02/2026",
      "qr_url": "http://us1.bot-hosting.net:21555/scan/DE25438F",
      "download_count": 0,
      "retake_used": false
    },
    {
      "id": "34c0df90-e490-4459-af41-794cc432326a",
      "pickup_code": "078A6B75",
      "filenames": [
        "20260207_033023_078A6B75_1.png",
        "20260207_033023_078A6B75_2.png"
      ],
      "timestamp": "2026-02-07T03:30:23.768404",
      "time_display": "03:30:23 07/02/2026",
      "qr_url": "http://us1.bot-hosting.net:21555/scan/078A6B75",
      "download_count": 0,
      "retake_used": false
    },
    {
      "id": "9b9c1463-cdb8-4fdc-a6ed-9934483d2fa8",
      "pickup_code": "104E2129",
      "filenames": [
        "20260207_033202_104E2129_1.png"
      ],
      "timestamp": "2026-02-07T03:32:02.353104",
      "time_display": "03:32:02 07/02/2026",
      "qr_url": "http://us1.bot-hosting.net:21555/scan/104E2129",
      "download_count": 0,
      "retake_used": false
    },
    {
      "id": "6ac30736-7b41-497a-b8e6-767ab265ce23",
      "pickup_code": "7A19D9F5",
      "filenames": [
        "20260207_035543_7A19D9F5_1.png",
        "20260207_035543_7A19D9F5_2.png"
      ],
      "timestamp": "2026-02-07T03:55:44.062601",
      "time_display": "03:55:44 07/02/2026",
      "qr_url": "http://us1.bot-hosting.net:21555/scan/7A19D9F5",
      "download_count": 0,
      "retake_used": false
    },
    {
      "id": "1f170d4c-e8b3-409e-92a8-f63ffd5ab3c0",
      "pickup_code": "9CE41876",
      "filenames": [
        "20260209_010513_9CE41876_1.png"
      ],
      "timestamp": "2026-02-09T01:05:13.979190",
      "time_display": "01:05:13 09/02/2026",
      "qr_url": "http://us1.bot-hosting.net:21555/scan/9CE41876",
      "download_count": 0,
      "retake_used": false
    }
  ],
  "stats": {
    "total_photos": 21,
    "total_downloads": 14,
    "total_sessions": 17
  }
}